early_stopping/__init__.py
early_stopping-0.1.3.dist-info/LICENSE
early_stopping-0.1.3.dist-info/METADATA
early_stopping-0.1.3.dist-info/WHEEL
early_stopping-0.1.3.dist-info/top_level.txt
early_stopping-0.1.3.dist-info/RECORD
