Metadata-Version: 2.1
Name: early-stopping
Version: 0.1.3
Summary: Early stopping for neural networks
Home-page: UNKNOWN
Author: Ovikx
License: UNKNOWN
Project-URL: Source code, https://github.com/Ovikx/early-stopping
Platform: UNKNOWN
Classifier: Programming Language :: Python :: 3
Classifier: License :: OSI Approved :: MIT License
Classifier: Operating System :: OS Independent
License-File: LICENSE
